boilerplate_tools/__init__.py
boilerplate_tools/src/__init__.py
boilerplate_tools/src/utils/__init__.py
boilerplate_tools/src/utils/config.py
boilerplate_tools/src/utils/json_io.py
boilerplate_tools/src/utils/path_handler.py
boilerplate_tools/src/utils/smart_format.py
boilerplate_tools-0.1.4.dist-info/METADATA
boilerplate_tools-0.1.4.dist-info/WHEEL
boilerplate_tools-0.1.4.dist-info/top_level.txt
boilerplate_tools-0.1.4.dist-info/RECORD
